{
    "f1-score": {
        "add_service": 0.0,
        "aneeda_opinion": 0.0,
        "business_address": 0.29820316387074186,
        "business_hours": 0.5987980751888379,
        "business_phone": 0.5892074750587486,
        "business_price": 0.0,
        "business_rating": 0.40429079839738563,
        "business_reviews": 0.5691342077483196,
        "business_search": 0.7970841651160946,
        "calendar_check_event": 0.8748186135284145,
        "calendar_create_event": 0.9294373038923153,
        "calendar_show_event": 0.7247304732933704,
        "call_history": 0.8862335616635637,
        "call_make": 0.8254390144841122,
        "cancel_dialogue": 0.0,
        "change_service": 0.0,
        "clock_time": 0.8972276961653632,
        "contact_open": 0.5682542606031469,
        "control_next": 0.0,
        "control_off": 0.0,
        "control_on": 0.4260715512696495,
        "control_pause": 0.4544770314897697,
        "control_previous": 0.3640731296702864,
        "control_repeat": 0.4727900908145356,
        "control_resume": 0.0,
        "control_stop": 0.228607363886167,
        "correction": 0.0,
        "email_check": 0.3234282822939546,
        "email_compose": 0.7817416386534798,
        "email_reply": 0.37912034207712536,
        "email_show": 0.8243959555171987,
        "email_summarize": 0.0,
        "filter_profanity": 0.0,
        "find_recipe": 0.0,
        "music_albums": 0.9721448599131662,
        "music_collection_add": 0.8688068514782143,
        "music_collection_view": 0.41867046034421435,
        "music_id": 0.6385536628147603,
        "music_info_concerts": 0.8636314467404985,
        "music_info_similar_artists": 0.8987986905977671,
        "music_play": 0.6583118569780962,
        "news_search": 0.6042767377812007,
        "no_intent_found": 0.566270797861201,
        "remove_service": 0.0,
        "restaurant_reservation": 0.0,
        "restaurant_search": 0.8606154715948621,
        "set_alarm": 0.0,
        "sports_follow_a_game": 0.7623933470738631,
        "sports_team_results": 0.7652593708914799,
        "sports_team_schedule": 0.7687313256711444,
        "sports_team_standing": 0.8829365423636986,
        "start_dialogue": 0.0,
        "transport_taxi_book": 0.5914668409601089,
        "transport_taxi_cancel": 0.8024922392725833,
        "transport_taxi_current_status": 0.5748699698877634,
        "transport_taxi_destination": 0.9031148974682619,
        "transport_taxi_estimate_travel_fare": 0.8403658886931639,
        "transport_taxi_estimate_travel_time": 0.8454538733297866,
        "transport_taxi_ride_history": 0.8049866930771143,
        "tv_listings": 0.7972702863504728,
        "tv_show_airings": 0.8786999766717728,
        "tv_show_cast": 0.5578375460153407,
        "tv_show_description": 0.5446572651871462,
        "tv_show_episode_summary": 0.8203191641206458,
        "tv_streaming_search": 0.8412588894144327,
        "weather_find": 0.8757891572453673,
        "weather_set_alert": 0.9268187189163686
    },
    "fc_error": {
        "add_service": 0.0,
        "aneeda_opinion": 0.0,
        "business_address": 0.991304347826087,
        "business_hours": 0.9879518072289156,
        "business_phone": 0.9896907216494846,
        "business_price": 0.9553072625698324,
        "business_rating": 0.9904761904761905,
        "business_reviews": 0.9148936170212766,
        "business_search": 0.575,
        "calendar_check_event": 0.9655172413793104,
        "calendar_create_event": 0.9411764705882353,
        "calendar_show_event": 0.717948717948718,
        "call_history": 0.9629629629629629,
        "call_make": 0.9130434782608695,
        "cancel_dialogue": 0.0,
        "change_service": 0.0,
        "clock_time": 0.7619047619047619,
        "contact_open": 0.7590361445783133,
        "control_next": 0.7981220657276995,
        "control_off": 0.8787878787878788,
        "control_on": 0.8561151079136691,
        "control_pause": 0.8018018018018018,
        "control_previous": 0.993006993006993,
        "control_repeat": 0.9354838709677419,
        "control_resume": 0.7455357142857143,
        "control_stop": 0.6887755102040817,
        "correction": 0.0,
        "email_check": 0.9329608938547486,
        "email_compose": 0.4,
        "email_reply": 0.8823529411764706,
        "email_show": 0.8333333333333334,
        "email_summarize": 0.0,
        "filter_profanity": 0.0,
        "find_recipe": 0.0,
        "music_albums": 0.0,
        "music_collection_add": 0.75,
        "music_collection_view": 0.7398373983739838,
        "music_id": 0.9838709677419355,
        "music_info_concerts": 0.8888888888888888,
        "music_info_similar_artists": 0.5483870967741935,
        "music_play": 0.7,
        "news_search": 0.625,
        "no_intent_found": 0.0,
        "remove_service": 0.0,
        "restaurant_reservation": 0.0,
        "restaurant_search": 0.6363636363636364,
        "set_alarm": 0.0,
        "sports_follow_a_game": 0.9411764705882353,
        "sports_team_results": 0.8181818181818182,
        "sports_team_schedule": 0.9024390243902439,
        "sports_team_standing": 0.92,
        "start_dialogue": 0.0,
        "transport_taxi_book": 0.5238095238095238,
        "transport_taxi_cancel": 0.9807692307692307,
        "transport_taxi_current_status": 0.9761904761904762,
        "transport_taxi_destination": 0.9473684210526315,
        "transport_taxi_estimate_travel_fare": 0.6666666666666666,
        "transport_taxi_estimate_travel_time": 0.9565217391304348,
        "transport_taxi_ride_history": 0.9824561403508771,
        "tv_listings": 0.6666666666666666,
        "tv_show_airings": 0.9696969696969697,
        "tv_show_cast": 0.9393939393939394,
        "tv_show_description": 0.8809523809523809,
        "tv_show_episode_summary": 0.9272727272727272,
        "tv_streaming_search": 0.8,
        "weather_find": 0.9,
        "weather_set_alert": 0.9090909090909091
    },
    "precision": {
        "add_service": 0.0,
        "aneeda_opinion": 0.0,
        "business_address": 0.3129251700680272,
        "business_hours": 0.7477477477477478,
        "business_phone": 0.925,
        "business_price": 0.0,
        "business_rating": 0.53125,
        "business_reviews": 0.6818181818181818,
        "business_search": 0.8301886792452831,
        "calendar_check_event": 0.8958333333333334,
        "calendar_create_event": 0.9668874172185431,
        "calendar_show_event": 0.6598360655737705,
        "call_history": 0.9448275862068966,
        "call_make": 0.8120805369127517,
        "cancel_dialogue": 0.0,
        "change_service": 0.0,
        "clock_time": 0.9132947976878613,
        "contact_open": 0.6232876712328768,
        "control_next": 0.0,
        "control_off": 0.0,
        "control_on": 0.7733333333333333,
        "control_pause": 0.44651162790697674,
        "control_previous": 0.86,
        "control_repeat": 0.3408360128617363,
        "control_resume": 0.0,
        "control_stop": 0.5074626865671642,
        "correction": 0.0,
        "email_check": 0.8333333333333334,
        "email_compose": 0.654275092936803,
        "email_reply": 0.9230769230769231,
        "email_show": 0.7188755020080321,
        "email_summarize": 0.0,
        "filter_profanity": 0.0,
        "find_recipe": 0.0,
        "music_albums": 0.9523809523809523,
        "music_collection_add": 0.7857142857142857,
        "music_collection_view": 0.6195652173913043,
        "music_id": 0.6428571428571429,
        "music_info_concerts": 0.8324607329842932,
        "music_info_similar_artists": 0.9411764705882353,
        "music_play": 0.521875,
        "news_search": 0.49469964664310956,
        "no_intent_found": 0.6546349466776046,
        "remove_service": 0.0,
        "restaurant_reservation": 0.0,
        "restaurant_search": 0.9465648854961832,
        "set_alarm": 0.0,
        "sports_follow_a_game": 0.8604651162790697,
        "sports_team_results": 0.6495726495726496,
        "sports_team_schedule": 0.7861635220125787,
        "sports_team_standing": 0.9171974522292994,
        "start_dialogue": 0.0,
        "transport_taxi_book": 0.4447513812154696,
        "transport_taxi_cancel": 0.9908256880733946,
        "transport_taxi_current_status": 0.4666666666666667,
        "transport_taxi_destination": 0.9202453987730062,
        "transport_taxi_estimate_travel_fare": 0.7344398340248963,
        "transport_taxi_estimate_travel_time": 0.8181818181818182,
        "transport_taxi_ride_history": 0.9130434782608695,
        "tv_listings": 0.6729857819905213,
        "tv_show_airings": 0.9776119402985075,
        "tv_show_cast": 0.7523809523809524,
        "tv_show_description": 0.42028985507246375,
        "tv_show_episode_summary": 0.9530201342281879,
        "tv_streaming_search": 0.7485029940119761,
        "weather_find": 0.8585858585858586,
        "weather_set_alert": 0.9113300492610837
    },
    "prevalence": {
        "add_service": 0.0,
        "aneeda_opinion": 0.0,
        "business_address": 0.015998400159984,
        "business_hours": 0.0164983501649835,
        "business_phone": 0.016998300169983,
        "business_price": 0.0170982901709829,
        "business_rating": 0.015498450154984501,
        "business_reviews": 0.017598240175982403,
        "business_search": 0.015498450154984501,
        "calendar_check_event": 0.019998000199980003,
        "calendar_create_event": 0.016198380161983803,
        "calendar_show_event": 0.0188981101889811,
        "call_history": 0.016298370162983702,
        "call_make": 0.014198580141985802,
        "cancel_dialogue": 0.0,
        "change_service": 0.0,
        "clock_time": 0.0173982601739826,
        "contact_open": 0.015398460153984602,
        "control_next": 0.016998300169983,
        "control_off": 0.0173982601739826,
        "control_on": 0.017698230176982303,
        "control_pause": 0.0184981501849815,
        "control_previous": 0.0184981501849815,
        "control_repeat": 0.013498650134986502,
        "control_resume": 0.016698330166983303,
        "control_stop": 0.0168983101689831,
        "correction": 0.0,
        "email_check": 0.0211978802119788,
        "email_compose": 0.017798220177982202,
        "email_reply": 0.0182981701829817,
        "email_show": 0.0183981601839816,
        "email_summarize": 0.0,
        "filter_profanity": 0.0,
        "find_recipe": 0.0,
        "music_albums": 0.015998400159984,
        "music_collection_add": 0.014598540145985401,
        "music_collection_view": 0.014798520147985201,
        "music_id": 0.0168983101689831,
        "music_info_concerts": 0.0174982501749825,
        "music_info_similar_artists": 0.020897910208979104,
        "music_play": 0.018098190180981903,
        "news_search": 0.0164983501649835,
        "no_intent_found": 0.07999200079992001,
        "remove_service": 0.0,
        "restaurant_reservation": 0.0,
        "restaurant_search": 0.014498550144985502,
        "set_alarm": 0.0,
        "sports_follow_a_game": 0.015898410158984102,
        "sports_team_results": 0.0160983901609839,
        "sports_team_schedule": 0.016198380161983803,
        "sports_team_standing": 0.016698330166983303,
        "start_dialogue": 0.0,
        "transport_taxi_book": 0.017198280171982803,
        "transport_taxi_cancel": 0.015898410158984102,
        "transport_taxi_current_status": 0.016698330166983303,
        "transport_taxi_destination": 0.016798320167983202,
        "transport_taxi_estimate_travel_fare": 0.0178982101789821,
        "transport_taxi_estimate_travel_time": 0.0183981601839816,
        "transport_taxi_ride_history": 0.0202979702029797,
        "tv_listings": 0.0143985601439856,
        "tv_show_airings": 0.016298370162983702,
        "tv_show_cast": 0.017198280171982803,
        "tv_show_description": 0.018198180181981802,
        "tv_show_episode_summary": 0.0192980701929807,
        "tv_streaming_search": 0.012898710128987101,
        "weather_find": 0.0187981201879812,
        "weather_set_alert": 0.019498050194980503
    },
    "recall": {
        "add_service": 0.0,
        "aneeda_opinion": 0.0,
        "business_address": 0.2857142857142857,
        "business_hours": 0.5,
        "business_phone": 0.4327485380116959,
        "business_price": 0.0,
        "business_rating": 0.3269230769230769,
        "business_reviews": 0.4891304347826087,
        "business_search": 0.7674418604651163,
        "calendar_check_event": 0.8557213930348259,
        "calendar_create_event": 0.8957055214723927,
        "calendar_show_event": 0.805,
        "call_history": 0.8353658536585366,
        "call_make": 0.8402777777777778,
        "cancel_dialogue": 0.0,
        "change_service": 0.0,
        "clock_time": 0.88268156424581,
        "contact_open": 0.5229885057471264,
        "control_next": 0.0,
        "control_off": 0.0,
        "control_on": 0.29441624365482233,
        "control_pause": 0.463768115942029,
        "control_previous": 0.23118279569892472,
        "control_repeat": 0.7737226277372263,
        "control_resume": 0.0,
        "control_stop": 0.14782608695652175,
        "correction": 0.0,
        "email_check": 0.20089285714285715,
        "email_compose": 0.9723756906077348,
        "email_reply": 0.23880597014925373,
        "email_show": 0.9675675675675676,
        "email_summarize": 0.0,
        "filter_profanity": 0.0,
        "find_recipe": 0.0,
        "music_albums": 0.9937888198757764,
        "music_collection_add": 0.9727891156462585,
        "music_collection_view": 0.31666666666666665,
        "music_id": 0.6352941176470588,
        "music_info_concerts": 0.8983050847457628,
        "music_info_similar_artists": 0.8609865470852018,
        "music_play": 0.893048128342246,
        "news_search": 0.7777777777777778,
        "no_intent_found": 0.4996869129618034,
        "remove_service": 0.0,
        "restaurant_reservation": 0.0,
        "restaurant_search": 0.7898089171974523,
        "set_alarm": 0.0,
        "sports_follow_a_game": 0.6851851851851852,
        "sports_team_results": 0.9325153374233128,
        "sports_team_schedule": 0.7530120481927711,
        "sports_team_standing": 0.8520710059171598,
        "start_dialogue": 0.0,
        "transport_taxi_book": 0.8846153846153846,
        "transport_taxi_cancel": 0.675,
        "transport_taxi_current_status": 0.75,
        "transport_taxi_destination": 0.8875739644970414,
        "transport_taxi_estimate_travel_fare": 0.9833333333333333,
        "transport_taxi_estimate_travel_time": 0.8756756756756757,
        "transport_taxi_ride_history": 0.7205882352941176,
        "tv_listings": 0.9793103448275862,
        "tv_show_airings": 0.7987804878048781,
        "tv_show_cast": 0.4438202247191011,
        "tv_show_description": 0.7754010695187166,
        "tv_show_episode_summary": 0.7208121827411168,
        "tv_streaming_search": 0.9615384615384616,
        "weather_find": 0.8947368421052632,
        "weather_set_alert": 0.9438775510204082
    },
    "specificity": {
        "add_service": 0.9987484355444305,
        "aneeda_opinion": 0.9925373134328358,
        "business_address": 0.8876529477196885,
        "business_hours": 0.9661016949152542,
        "business_phone": 0.9925373134328358,
        "business_price": 0.9987484355444305,
        "business_rating": 0.9466192170818505,
        "business_reviews": 0.95,
        "business_search": 0.9672727272727273,
        "calendar_check_event": 0.9755501222493888,
        "calendar_create_event": 0.9937733499377335,
        "calendar_show_event": 0.905788876276958,
        "call_history": 0.9900744416873449,
        "call_make": 0.9661016949152542,
        "cancel_dialogue": 0.9987484355444305,
        "change_service": 0.9950124688279302,
        "clock_time": 0.981549815498155,
        "contact_open": 0.9355216881594373,
        "control_next": 0.9987484355444305,
        "control_off": 0.9987484355444305,
        "control_on": 0.9791411042944785,
        "control_pause": 0.8702290076335878,
        "control_previous": 0.991304347826087,
        "control_repeat": 0.7956131605184447,
        "control_resume": 0.9987484355444305,
        "control_stop": 0.9602888086642599,
        "correction": 0.9987484355444305,
        "email_check": 0.9888475836431226,
        "email_compose": 0.8956228956228957,
        "email_reply": 0.9950124688279302,
        "email_show": 0.9193548387096774,
        "email_summarize": 0.869281045751634,
        "filter_profanity": 0.9987484355444305,
        "find_recipe": 0.9987484355444305,
        "music_albums": 0.9900744416873449,
        "music_collection_add": 0.953405017921147,
        "music_collection_view": 0.957983193277311,
        "music_id": 0.9300699300699301,
        "music_info_concerts": 0.9614457831325302,
        "music_info_similar_artists": 0.9851851851851852,
        "music_play": 0.8391167192429022,
        "news_search": 0.8480340063761955,
        "no_intent_found": 0.6546349466776046,
        "remove_service": 0.9987484355444305,
        "restaurant_reservation": 0.9987484355444305,
        "restaurant_search": 0.991304347826087,
        "set_alarm": 0.9937733499377335,
        "sports_follow_a_game": 0.9779411764705882,
        "sports_team_results": 0.9068181818181819,
        "sports_team_schedule": 0.9591346153846154,
        "sports_team_standing": 0.9839704069050554,
        "start_dialogue": 0.9987484355444305,
        "transport_taxi_book": 0.7987987987987988,
        "transport_taxi_cancel": 0.9987484355444305,
        "transport_taxi_current_status": 0.8471337579617835,
        "transport_taxi_destination": 0.9839704069050554,
        "transport_taxi_estimate_travel_fare": 0.925754060324826,
        "transport_taxi_estimate_travel_time": 0.9568345323741008,
        "transport_taxi_ride_history": 0.9827586206896551,
        "tv_listings": 0.9204152249134948,
        "tv_show_airings": 0.9962546816479401,
        "tv_show_cast": 0.9684466019417476,
        "tv_show_description": 0.7995991983967936,
        "tv_show_episode_summary": 0.991304347826087,
        "tv_streaming_search": 0.95,
        "weather_find": 0.9661016949152542,
        "weather_set_alert": 0.9779411764705882
    },
    "tc_error": {
        "add_service": 0.0,
        "aneeda_opinion": 0.8333333333333334,
        "business_address": 0.9900990099009901,
        "business_hours": 0.9642857142857143,
        "business_phone": 0.8333333333333334,
        "business_price": 0.0,
        "business_rating": 0.9777777777777777,
        "business_reviews": 0.9761904761904762,
        "business_search": 0.9629629629629629,
        "calendar_check_event": 0.95,
        "calendar_create_event": 0.8,
        "calendar_show_event": 0.9879518072289156,
        "call_history": 0.875,
        "call_make": 0.8928571428571429,
        "cancel_dialogue": 0.0,
        "change_service": 0.75,
        "clock_time": 0.9333333333333333,
        "contact_open": 0.9818181818181818,
        "control_next": 0.0,
        "control_off": 0.0,
        "control_on": 0.9411764705882353,
        "control_pause": 0.9915966386554622,
        "control_previous": 0.8571428571428571,
        "control_repeat": 0.9951219512195122,
        "control_resume": 0.0,
        "control_stop": 0.9696969696969697,
        "correction": 0.0,
        "email_check": 0.8888888888888888,
        "email_compose": 0.989247311827957,
        "email_reply": 0.75,
        "email_show": 0.9857142857142858,
        "email_summarize": 0.9916666666666667,
        "filter_profanity": 0.0,
        "find_recipe": 0.0,
        "music_albums": 0.875,
        "music_collection_add": 0.9743589743589743,
        "music_collection_view": 0.9714285714285714,
        "music_id": 0.9833333333333333,
        "music_info_concerts": 0.96875,
        "music_info_similar_artists": 0.9166666666666666,
        "music_play": 0.9934640522875817,
        "news_search": 0.993006993006993,
        "no_intent_found": 0.997624703087886,
        "remove_service": 0.0,
        "restaurant_reservation": 0.0,
        "restaurant_search": 0.8571428571428571,
        "set_alarm": 0.8,
        "sports_follow_a_game": 0.9444444444444444,
        "sports_team_results": 0.9878048780487805,
        "sports_team_schedule": 0.9705882352941176,
        "sports_team_standing": 0.9230769230769231,
        "start_dialogue": 0.0,
        "transport_taxi_book": 0.9950248756218906,
        "transport_taxi_cancel": 0.0,
        "transport_taxi_current_status": 0.9930555555555556,
        "transport_taxi_destination": 0.9230769230769231,
        "transport_taxi_estimate_travel_fare": 0.984375,
        "transport_taxi_estimate_travel_time": 0.9722222222222222,
        "transport_taxi_ride_history": 0.9285714285714286,
        "tv_listings": 0.9855072463768116,
        "tv_show_airings": 0.6666666666666666,
        "tv_show_cast": 0.9615384615384616,
        "tv_show_description": 0.995,
        "tv_show_episode_summary": 0.8571428571428571,
        "tv_streaming_search": 0.9761904761904762,
        "weather_find": 0.9642857142857143,
        "weather_set_alert": 0.9444444444444444
    }
}